pibrella/__init__.py
pibrella/pins.py
pibrella-1.4.1.dist-info/LICENSE.txt
pibrella-1.4.1.dist-info/METADATA
pibrella-1.4.1.dist-info/WHEEL
pibrella-1.4.1.dist-info/top_level.txt
pibrella-1.4.1.dist-info/RECORD
